<Properties StartupConfiguration="{5CC9B06D-4EBF-4D7C-B7F9-EB9B76BF679E}|Default">
  <MonoDevelop.Ide.ItemProperties.Week3 FirstBuild="True" PreferredExecutionTarget="MonoDevelop.Default" />
  <MonoDevelop.Ide.Workbench ActiveDocument="gitignore.txt">
    <Files>
      <File FileName="Week3/Program.cs" Line="1" Column="1" />
      <File FileName="gitignore.txt" Line="11" Column="16" />
    </Files>
    <Pads>
      <Pad Id="ProjectPad">
        <State name="__root__">
          <Node name="Week3" expanded="True" selected="True">
            <Node name="Solution Items" expanded="True" />
            <Node name="Week3" expanded="True" />
          </Node>
        </State>
      </Pad>
    </Pads>
  </MonoDevelop.Ide.Workbench>
  <MonoDevelop.Ide.DebuggingService.PinnedWatches />
  <MonoDevelop.Ide.Workspace ActiveConfiguration="Debug|anycpu" />
  <MonoDevelop.Ide.DebuggingService.Breakpoints>
    <BreakpointStore />
  </MonoDevelop.Ide.DebuggingService.Breakpoints>
  <MultiItemStartupConfigurations />
</Properties>